{"nodes": [{"id": "scoring_method", "label": "Scoring Method", "file_type": "code", "source_file": "src/agent/skills/evaluate/scoring/SKILL.md", "source_location": null}, {"id": "technical_accuracy", "label": "Technical Accuracy Dimension", "file_type": "code", "source_file": "src/agent/skills/evaluate/scoring/SKILL.md", "source_location": null}, {"id": "completeness_dimension", "label": "Completeness Dimension", "file_type": "code", "source_file": "src/agent/skills/evaluate/scoring/SKILL.md", "source_location": null}, {"id": "depth_dimension", "label": "Depth Dimension", "file_type": "code", "source_file": "src/agent/skills/evaluate/scoring/SKILL.md", "source_location": null}, {"id": "expression_clarity", "label": "Expression Clarity Dimension", "file_type": "code", "source_file": "src/agent/skills/evaluate/scoring/SKILL.md", "source_location": null}, {"id": "evaluate_agent", "label": "Evaluate Agent", "file_type": "code", "source_file": "src/agent/skills/evaluate/scoring/SKILL.md", "source_location": null}], "edges": [{"source": "scoring_method", "target": "technical_accuracy", "relation": "contains_dimension", "confidence": "EXTRACTED", "confidence_score": 1.0, "source_file": "src/agent/skills/evaluate/scoring/SKILL.md", "source_location": null, "weight": 1.0}, {"source": "scoring_method", "target": "completeness_dimension", "relation": "contains_dimension", "confidence": "EXTRACTED", "confidence_score": 1.0, "source_file": "src/agent/skills/evaluate/scoring/SKILL.md", "source_location": null, "weight": 1.0}, {"source": "scoring_method", "target": "depth_dimension", "relation": "contains_dimension", "confidence": "EXTRACTED", "confidence_score": 1.0, "source_file": "src/agent/skills/evaluate/scoring/SKILL.md", "source_location": null, "weight": 1.0}, {"source": "scoring_method", "target": "expression_clarity", "relation": "contains_dimension", "confidence": "EXTRACTED", "confidence_score": 1.0, "source_file": "src/agent/skills/evaluate/scoring/SKILL.md", "source_location": null, "weight": 1.0}, {"source": "evaluate_agent", "target": "scoring_method", "relation": "uses", "confidence": "EXTRACTED", "confidence_score": 1.0, "source_file": "src/agent/skills/evaluate/scoring/SKILL.md", "source_location": null, "weight": 1.0}], "hyperedges": [{"id": "scoring_dimensions", "label": "Scoring Dimensions", "nodes": ["scoring_method", "technical_accuracy", "completeness_dimension", "depth_dimension", "expression_clarity"], "relation": "participate_in", "confidence": "EXTRACTED", "confidence_score": 1.0, "source_file": "src/agent/skills/evaluate/scoring/SKILL.md"}]}