{"nodes": [{"id": "src_api_models_py", "label": "models.py", "file_type": "code", "source_file": "src\\api\\models.py", "source_location": "L1"}, {"id": "models_startinterviewrequest", "label": "StartInterviewRequest", "file_type": "code", "source_file": "src\\api\\models.py", "source_location": "L16"}, {"id": "basemodel", "label": "BaseModel", "file_type": "code", "source_file": "", "source_location": ""}, {"id": "models_submitanswerrequest", "label": "SubmitAnswerRequest", "file_type": "code", "source_file": "src\\api\\models.py", "source_location": "L27"}, {"id": "models_starttrainingrequest", "label": "StartTrainingRequest", "file_type": "code", "source_file": "src\\api\\models.py", "source_location": "L34"}, {"id": "models_ragqueryrequest", "label": "RagQueryRequest", "file_type": "code", "source_file": "src\\api\\models.py", "source_location": "L42"}, {"id": "models_buildknowledgerequest", "label": "BuildKnowledgeRequest", "file_type": "code", "source_file": "src\\api\\models.py", "source_location": "L49"}, {"id": "models_feedbackdata", "label": "FeedbackData", "file_type": "code", "source_file": "src\\api\\models.py", "source_location": "L62"}, {"id": "models_questiondata", "label": "QuestionData", "file_type": "code", "source_file": "src\\api\\models.py", "source_location": "L70"}, {"id": "models_qaresponse", "label": "QAResponse", "file_type": "code", "source_file": "src\\api\\models.py", "source_location": "L79"}, {"id": "models_startinterviewresponse", "label": "StartInterviewResponse", "file_type": "code", "source_file": "src\\api\\models.py", "source_location": "L90"}, {"id": "models_interviewresult", "label": "InterviewResult", "file_type": "code", "source_file": "src\\api\\models.py", "source_location": "L97"}, {"id": "models_trainingresult", "label": "TrainingResult", "file_type": "code", "source_file": "src\\api\\models.py", "source_location": "L106"}, {"id": "models_ragqueryresult", "label": "RagQueryResult", "file_type": "code", "source_file": "src\\api\\models.py", "source_location": "L115"}, {"id": "models_buildknowledgeresult", "label": "BuildKnowledgeResult", "file_type": "code", "source_file": "src\\api\\models.py", "source_location": "L122"}, {"id": "models_sseevent", "label": "SSEEvent", "file_type": "code", "source_file": "src\\api\\models.py", "source_location": "L133"}, {"id": "models_ssemessage", "label": "SSEMessage", "file_type": "code", "source_file": "src\\api\\models.py", "source_location": "L139"}, {"id": "models_snapshotrequest", "label": "SnapshotRequest", "file_type": "code", "source_file": "src\\api\\models.py", "source_location": "L150"}, {"id": "models_restorerequest", "label": "RestoreRequest", "file_type": "code", "source_file": "src\\api\\models.py", "source_location": "L156"}, {"id": "models_snapshotresponse", "label": "SnapshotResponse", "file_type": "code", "source_file": "src\\api\\models.py", "source_location": "L162"}, {"id": "models_rationale_1", "label": "Pydantic Models for FastAPI Interview API  \u9762\u8bd5 API \u8bf7\u6c42/\u54cd\u5e94\u6a21\u578b", "file_type": "rationale", "source_file": "src\\api\\models.py", "source_location": "L1"}], "edges": [{"source": "src_api_models_py", "target": "typing", "relation": "imports_from", "confidence": "EXTRACTED", "source_file": "src\\api\\models.py", "source_location": "L7", "weight": 1.0}, {"source": "src_api_models_py", "target": "datetime", "relation": "imports_from", "confidence": "EXTRACTED", "source_file": "src\\api\\models.py", "source_location": "L8", "weight": 1.0}, {"source": "src_api_models_py", "target": "pydantic", "relation": "imports_from", "confidence": "EXTRACTED", "source_file": "src\\api\\models.py", "source_location": "L9", "weight": 1.0}, {"source": "src_api_models_py", "target": "models_startinterviewrequest", "relation": "contains", "confidence": "EXTRACTED", "source_file": "src\\api\\models.py", "source_location": "L16", "weight": 1.0}, {"source": "models_startinterviewrequest", "target": "basemodel", "relation": "inherits", "confidence": "EXTRACTED", "source_file": "src\\api\\models.py", "source_location": "L16", "weight": 1.0}, {"source": "src_api_models_py", "target": "models_submitanswerrequest", "relation": "contains", "confidence": "EXTRACTED", "source_file": "src\\api\\models.py", "source_location": "L27", "weight": 1.0}, {"source": "models_submitanswerrequest", "target": "basemodel", "relation": "inherits", "confidence": "EXTRACTED", "source_file": "src\\api\\models.py", "source_location": "L27", "weight": 1.0}, {"source": "src_api_models_py", "target": "models_starttrainingrequest", "relation": "contains", "confidence": "EXTRACTED", "source_file": "src\\api\\models.py", "source_location": "L34", "weight": 1.0}, {"source": "models_starttrainingrequest", "target": "basemodel", "relation": "inherits", "confidence": "EXTRACTED", "source_file": "src\\api\\models.py", "source_location": "L34", "weight": 1.0}, {"source": "src_api_models_py", "target": "models_ragqueryrequest", "relation": "contains", "confidence": "EXTRACTED", "source_file": "src\\api\\models.py", "source_location": "L42", "weight": 1.0}, {"source": "models_ragqueryrequest", "target": "basemodel", "relation": "inherits", "confidence": "EXTRACTED", "source_file": "src\\api\\models.py", "source_location": "L42", "weight": 1.0}, {"source": "src_api_models_py", "target": "models_buildknowledgerequest", "relation": "contains", "confidence": "EXTRACTED", "source_file": "src\\api\\models.py", "source_location": "L49", "weight": 1.0}, {"source": "models_buildknowledgerequest", "target": "basemodel", "relation": "inherits", "confidence": "EXTRACTED", "source_file": "src\\api\\models.py", "source_location": "L49", "weight": 1.0}, {"source": "src_api_models_py", "target": "models_feedbackdata", "relation": "contains", "confidence": "EXTRACTED", "source_file": "src\\api\\models.py", "source_location": "L62", "weight": 1.0}, {"source": "models_feedbackdata", "target": "basemodel", "relation": "inherits", "confidence": "EXTRACTED", "source_file": "src\\api\\models.py", "source_location": "L62", "weight": 1.0}, {"source": "src_api_models_py", "target": "models_questiondata", "relation": "contains", "confidence": "EXTRACTED", "source_file": "src\\api\\models.py", "source_location": "L70", "weight": 1.0}, {"source": "models_questiondata", "target": "basemodel", "relation": "inherits", "confidence": "EXTRACTED", "source_file": "src\\api\\models.py", "source_location": "L70", "weight": 1.0}, {"source": "src_api_models_py", "target": "models_qaresponse", "relation": "contains", "confidence": "EXTRACTED", "source_file": "src\\api\\models.py", "source_location": "L79", "weight": 1.0}, {"source": "models_qaresponse", "target": "basemodel", "relation": "inherits", "confidence": "EXTRACTED", "source_file": "src\\api\\models.py", "source_location": "L79", "weight": 1.0}, {"source": "src_api_models_py", "target": "models_startinterviewresponse", "relation": "contains", "confidence": "EXTRACTED", "source_file": "src\\api\\models.py", "source_location": "L90", "weight": 1.0}, {"source": "models_startinterviewresponse", "target": "basemodel", "relation": "inherits", "confidence": "EXTRACTED", "source_file": "src\\api\\models.py", "source_location": "L90", "weight": 1.0}, {"source": "src_api_models_py", "target": "models_interviewresult", "relation": "contains", "confidence": "EXTRACTED", "source_file": "src\\api\\models.py", "source_location": "L97", "weight": 1.0}, {"source": "models_interviewresult", "target": "basemodel", "relation": "inherits", "confidence": "EXTRACTED", "source_file": "src\\api\\models.py", "source_location": "L97", "weight": 1.0}, {"source": "src_api_models_py", "target": "models_trainingresult", "relation": "contains", "confidence": "EXTRACTED", "source_file": "src\\api\\models.py", "source_location": "L106", "weight": 1.0}, {"source": "models_trainingresult", "target": "basemodel", "relation": "inherits", "confidence": "EXTRACTED", "source_file": "src\\api\\models.py", "source_location": "L106", "weight": 1.0}, {"source": "src_api_models_py", "target": "models_ragqueryresult", "relation": "contains", "confidence": "EXTRACTED", "source_file": "src\\api\\models.py", "source_location": "L115", "weight": 1.0}, {"source": "models_ragqueryresult", "target": "basemodel", "relation": "inherits", "confidence": "EXTRACTED", "source_file": "src\\api\\models.py", "source_location": "L115", "weight": 1.0}, {"source": "src_api_models_py", "target": "models_buildknowledgeresult", "relation": "contains", "confidence": "EXTRACTED", "source_file": "src\\api\\models.py", "source_location": "L122", "weight": 1.0}, {"source": "models_buildknowledgeresult", "target": "basemodel", "relation": "inherits", "confidence": "EXTRACTED", "source_file": "src\\api\\models.py", "source_location": "L122", "weight": 1.0}, {"source": "src_api_models_py", "target": "models_sseevent", "relation": "contains", "confidence": "EXTRACTED", "source_file": "src\\api\\models.py", "source_location": "L133", "weight": 1.0}, {"source": "models_sseevent", "target": "basemodel", "relation": "inherits", "confidence": "EXTRACTED", "source_file": "src\\api\\models.py", "source_location": "L133", "weight": 1.0}, {"source": "src_api_models_py", "target": "models_ssemessage", "relation": "contains", "confidence": "EXTRACTED", "source_file": "src\\api\\models.py", "source_location": "L139", "weight": 1.0}, {"source": "models_ssemessage", "target": "basemodel", "relation": "inherits", "confidence": "EXTRACTED", "source_file": "src\\api\\models.py", "source_location": "L139", "weight": 1.0}, {"source": "src_api_models_py", "target": "models_snapshotrequest", "relation": "contains", "confidence": "EXTRACTED", "source_file": "src\\api\\models.py", "source_location": "L150", "weight": 1.0}, {"source": "models_snapshotrequest", "target": "basemodel", "relation": "inherits", "confidence": "EXTRACTED", "source_file": "src\\api\\models.py", "source_location": "L150", "weight": 1.0}, {"source": "src_api_models_py", "target": "models_restorerequest", "relation": "contains", "confidence": "EXTRACTED", "source_file": "src\\api\\models.py", "source_location": "L156", "weight": 1.0}, {"source": "models_restorerequest", "target": "basemodel", "relation": "inherits", "confidence": "EXTRACTED", "source_file": "src\\api\\models.py", "source_location": "L156", "weight": 1.0}, {"source": "src_api_models_py", "target": "models_snapshotresponse", "relation": "contains", "confidence": "EXTRACTED", "source_file": "src\\api\\models.py", "source_location": "L162", "weight": 1.0}, {"source": "models_snapshotresponse", "target": "basemodel", "relation": "inherits", "confidence": "EXTRACTED", "source_file": "src\\api\\models.py", "source_location": "L162", "weight": 1.0}, {"source": "models_rationale_1", "target": "src_api_models_py", "relation": "rationale_for", "confidence": "EXTRACTED", "source_file": "src\\api\\models.py", "source_location": "L1", "weight": 1.0}]}