{"nodes": [{"id": "tests_unit_test_context_catch_py", "label": "test_context_catch.py", "file_type": "code", "source_file": "tests\\unit\\test_context_catch.py", "source_location": "L1"}, {"id": "test_context_catch_engine", "label": "engine()", "file_type": "code", "source_file": "tests\\unit\\test_context_catch.py", "source_location": "L21"}, {"id": "test_context_catch_mock_state", "label": "mock_state()", "file_type": "code", "source_file": "tests\\unit\\test_context_catch.py", "source_location": "L26"}, {"id": "test_context_catch_testextractprogress", "label": "TestExtractProgress", "file_type": "code", "source_file": "tests\\unit\\test_context_catch.py", "source_location": "L47"}, {"id": "test_context_catch_testextractprogress_test_extract_progress_basic", "label": ".test_extract_progress_basic()", "file_type": "code", "source_file": "tests\\unit\\test_context_catch.py", "source_location": "L50"}, {"id": "test_context_catch_testextractprogress_test_extract_progress_question_index", "label": ".test_extract_progress_question_index()", "file_type": "code", "source_file": "tests\\unit\\test_context_catch.py", "source_location": "L56"}, {"id": "test_context_catch_testextractprogress_test_extract_progress_followup_chain", "label": ".test_extract_progress_followup_chain()", "file_type": "code", "source_file": "tests\\unit\\test_context_catch.py", "source_location": "L61"}, {"id": "test_context_catch_testextractevaluation", "label": "TestExtractEvaluation", "file_type": "code", "source_file": "tests\\unit\\test_context_catch.py", "source_location": "L67"}, {"id": "test_context_catch_testextractevaluation_test_extract_evaluation_series_scores", "label": ".test_extract_evaluation_series_scores()", "file_type": "code", "source_file": "tests\\unit\\test_context_catch.py", "source_location": "L70"}, {"id": "test_context_catch_testextractevaluation_test_extract_evaluation_error_count", "label": ".test_extract_evaluation_error_count()", "file_type": "code", "source_file": "tests\\unit\\test_context_catch.py", "source_location": "L79"}, {"id": "test_context_catch_testextractevaluation_test_extract_evaluation_empty_answers", "label": ".test_extract_evaluation_empty_answers()", "file_type": "code", "source_file": "tests\\unit\\test_context_catch.py", "source_location": "L83"}, {"id": "test_context_catch_testrediskeyfunctions", "label": "TestRedisKeyFunctions", "file_type": "code", "source_file": "tests\\unit\\test_context_catch.py", "source_location": "L96"}, {"id": "test_context_catch_testrediskeyfunctions_test_snapshot_key", "label": ".test_snapshot_key()", "file_type": "code", "source_file": "tests\\unit\\test_context_catch.py", "source_location": "L99"}, {"id": "test_context_catch_testrediskeyfunctions_test_version_key", "label": ".test_version_key()", "file_type": "code", "source_file": "tests\\unit\\test_context_catch.py", "source_location": "L103"}, {"id": "test_context_catch_testcompress", "label": "TestCompress", "file_type": "code", "source_file": "tests\\unit\\test_context_catch.py", "source_location": "L108"}, {"id": "test_context_catch_test_compress_generates_snapshot", "label": "test_compress_generates_snapshot()", "file_type": "code", "source_file": "tests\\unit\\test_context_catch.py", "source_location": "L112"}, {"id": "test_context_catch_testrestore", "label": "TestRestore", "file_type": "code", "source_file": "tests\\unit\\test_context_catch.py", "source_location": "L139"}, {"id": "test_context_catch_test_restore_full_mode", "label": "test_restore_full_mode()", "file_type": "code", "source_file": "tests\\unit\\test_context_catch.py", "source_location": "L143"}, {"id": "test_context_catch_test_restore_key_points_mode", "label": "test_restore_key_points_mode()", "file_type": "code", "source_file": "tests\\unit\\test_context_catch.py", "source_location": "L167"}, {"id": "test_context_catch_test_restore_fallback_to_pg", "label": "test_restore_fallback_to_pg()", "file_type": "code", "source_file": "tests\\unit\\test_context_catch.py", "source_location": "L191"}, {"id": "test_context_catch_test_restore_session_not_found", "label": "test_restore_session_not_found()", "file_type": "code", "source_file": "tests\\unit\\test_context_catch.py", "source_location": "L213"}, {"id": "test_context_catch_testsummarizeanswers", "label": "TestSummarizeAnswers", "file_type": "code", "source_file": "tests\\unit\\test_context_catch.py", "source_location": "L224"}, {"id": "test_context_catch_testsummarizeanswers_test_summarize_answers_empty", "label": ".test_summarize_answers_empty()", "file_type": "code", "source_file": "tests\\unit\\test_context_catch.py", "source_location": "L227"}, {"id": "test_context_catch_testsummarizeanswers_test_summarize_answers_multiple", "label": ".test_summarize_answers_multiple()", "file_type": "code", "source_file": "tests\\unit\\test_context_catch.py", "source_location": "L231"}, {"id": "test_context_catch_testsummarizefeedbacks", "label": "TestSummarizeFeedbacks", "file_type": "code", "source_file": "tests\\unit\\test_context_catch.py", "source_location": "L237"}, {"id": "test_context_catch_testsummarizefeedbacks_test_summarize_feedbacks_empty", "label": ".test_summarize_feedbacks_empty()", "file_type": "code", "source_file": "tests\\unit\\test_context_catch.py", "source_location": "L240"}, {"id": "test_context_catch_testsummarizefeedbacks_test_summarize_feedbacks_multiple", "label": ".test_summarize_feedbacks_multiple()", "file_type": "code", "source_file": "tests\\unit\\test_context_catch.py", "source_location": "L244"}, {"id": "test_context_catch_rationale_1", "label": "Unit tests for ContextCatchEngine", "file_type": "rationale", "source_file": "tests\\unit\\test_context_catch.py", "source_location": "L1"}, {"id": "test_context_catch_rationale_48", "label": "Test _extract_progress method", "file_type": "rationale", "source_file": "tests\\unit\\test_context_catch.py", "source_location": "L48"}, {"id": "test_context_catch_rationale_68", "label": "Test _extract_evaluation method", "file_type": "rationale", "source_file": "tests\\unit\\test_context_catch.py", "source_location": "L68"}, {"id": "test_context_catch_rationale_97", "label": "Test Redis key generation functions", "file_type": "rationale", "source_file": "tests\\unit\\test_context_catch.py", "source_location": "L97"}, {"id": "test_context_catch_rationale_225", "label": "Test answer summarization", "file_type": "rationale", "source_file": "tests\\unit\\test_context_catch.py", "source_location": "L225"}, {"id": "test_context_catch_rationale_238", "label": "Test feedback summarization", "file_type": "rationale", "source_file": "tests\\unit\\test_context_catch.py", "source_location": "L238"}], "edges": [{"source": "tests_unit_test_context_catch_py", "target": "pytest", "relation": "imports", "confidence": "EXTRACTED", "source_file": "tests\\unit\\test_context_catch.py", "source_location": "L5", "weight": 1.0}, {"source": "tests_unit_test_context_catch_py", "target": "datetime", "relation": "imports_from", "confidence": "EXTRACTED", "source_file": "tests\\unit\\test_context_catch.py", "source_location": "L6", "weight": 1.0}, {"source": "tests_unit_test_context_catch_py", "target": "unittest_mock", "relation": "imports_from", "confidence": "EXTRACTED", "source_file": "tests\\unit\\test_context_catch.py", "source_location": "L7", "weight": 1.0}, {"source": "tests_unit_test_context_catch_py", "target": "src_core_context_catch", "relation": "imports_from", "confidence": "EXTRACTED", "source_file": "tests\\unit\\test_context_catch.py", "source_location": "L8", "weight": 1.0}, {"source": "tests_unit_test_context_catch_py", "target": "src_agent_state", "relation": "imports_from", "confidence": "EXTRACTED", "source_file": "tests\\unit\\test_context_catch.py", "source_location": "L9", "weight": 1.0}, {"source": "tests_unit_test_context_catch_py", "target": "test_context_catch_engine", "relation": "contains", "confidence": "EXTRACTED", "source_file": "tests\\unit\\test_context_catch.py", "source_location": "L21", "weight": 1.0}, {"source": "tests_unit_test_context_catch_py", "target": "test_context_catch_mock_state", "relation": "contains", "confidence": "EXTRACTED", "source_file": "tests\\unit\\test_context_catch.py", "source_location": "L26", "weight": 1.0}, {"source": "tests_unit_test_context_catch_py", "target": "test_context_catch_testextractprogress", "relation": "contains", "confidence": "EXTRACTED", "source_file": "tests\\unit\\test_context_catch.py", "source_location": "L47", "weight": 1.0}, {"source": "test_context_catch_testextractprogress", "target": "test_context_catch_testextractprogress_test_extract_progress_basic", "relation": "method", "confidence": "EXTRACTED", "source_file": "tests\\unit\\test_context_catch.py", "source_location": "L50", "weight": 1.0}, {"source": "test_context_catch_testextractprogress", "target": "test_context_catch_testextractprogress_test_extract_progress_question_index", "relation": "method", "confidence": "EXTRACTED", "source_file": "tests\\unit\\test_context_catch.py", "source_location": "L56", "weight": 1.0}, {"source": "test_context_catch_testextractprogress", "target": "test_context_catch_testextractprogress_test_extract_progress_followup_chain", "relation": "method", "confidence": "EXTRACTED", "source_file": "tests\\unit\\test_context_catch.py", "source_location": "L61", "weight": 1.0}, {"source": "tests_unit_test_context_catch_py", "target": "test_context_catch_testextractevaluation", "relation": "contains", "confidence": "EXTRACTED", "source_file": "tests\\unit\\test_context_catch.py", "source_location": "L67", "weight": 1.0}, {"source": "test_context_catch_testextractevaluation", "target": "test_context_catch_testextractevaluation_test_extract_evaluation_series_scores", "relation": "method", "confidence": "EXTRACTED", "source_file": "tests\\unit\\test_context_catch.py", "source_location": "L70", "weight": 1.0}, {"source": "test_context_catch_testextractevaluation", "target": "test_context_catch_testextractevaluation_test_extract_evaluation_error_count", "relation": "method", "confidence": "EXTRACTED", "source_file": "tests\\unit\\test_context_catch.py", "source_location": "L79", "weight": 1.0}, {"source": "test_context_catch_testextractevaluation", "target": "test_context_catch_testextractevaluation_test_extract_evaluation_empty_answers", "relation": "method", "confidence": "EXTRACTED", "source_file": "tests\\unit\\test_context_catch.py", "source_location": "L83", "weight": 1.0}, {"source": "tests_unit_test_context_catch_py", "target": "test_context_catch_testrediskeyfunctions", "relation": "contains", "confidence": "EXTRACTED", "source_file": "tests\\unit\\test_context_catch.py", "source_location": "L96", "weight": 1.0}, {"source": "test_context_catch_testrediskeyfunctions", "target": "test_context_catch_testrediskeyfunctions_test_snapshot_key", "relation": "method", "confidence": "EXTRACTED", "source_file": "tests\\unit\\test_context_catch.py", "source_location": "L99", "weight": 1.0}, {"source": "test_context_catch_testrediskeyfunctions", "target": "test_context_catch_testrediskeyfunctions_test_version_key", "relation": "method", "confidence": "EXTRACTED", "source_file": "tests\\unit\\test_context_catch.py", "source_location": "L103", "weight": 1.0}, {"source": "tests_unit_test_context_catch_py", "target": "test_context_catch_testcompress", "relation": "contains", "confidence": "EXTRACTED", "source_file": "tests\\unit\\test_context_catch.py", "source_location": "L108", "weight": 1.0}, {"source": "tests_unit_test_context_catch_py", "target": "test_context_catch_test_compress_generates_snapshot", "relation": "contains", "confidence": "EXTRACTED", "source_file": "tests\\unit\\test_context_catch.py", "source_location": "L112", "weight": 1.0}, {"source": "tests_unit_test_context_catch_py", "target": "test_context_catch_testrestore", "relation": "contains", "confidence": "EXTRACTED", "source_file": "tests\\unit\\test_context_catch.py", "source_location": "L139", "weight": 1.0}, {"source": "tests_unit_test_context_catch_py", "target": "test_context_catch_test_restore_full_mode", "relation": "contains", "confidence": "EXTRACTED", "source_file": "tests\\unit\\test_context_catch.py", "source_location": "L143", "weight": 1.0}, {"source": "tests_unit_test_context_catch_py", "target": "test_context_catch_test_restore_key_points_mode", "relation": "contains", "confidence": "EXTRACTED", "source_file": "tests\\unit\\test_context_catch.py", "source_location": "L167", "weight": 1.0}, {"source": "tests_unit_test_context_catch_py", "target": "test_context_catch_test_restore_fallback_to_pg", "relation": "contains", "confidence": "EXTRACTED", "source_file": "tests\\unit\\test_context_catch.py", "source_location": "L191", "weight": 1.0}, {"source": "tests_unit_test_context_catch_py", "target": "test_context_catch_test_restore_session_not_found", "relation": "contains", "confidence": "EXTRACTED", "source_file": "tests\\unit\\test_context_catch.py", "source_location": "L213", "weight": 1.0}, {"source": "tests_unit_test_context_catch_py", "target": "test_context_catch_testsummarizeanswers", "relation": "contains", "confidence": "EXTRACTED", "source_file": "tests\\unit\\test_context_catch.py", "source_location": "L224", "weight": 1.0}, {"source": "test_context_catch_testsummarizeanswers", "target": "test_context_catch_testsummarizeanswers_test_summarize_answers_empty", "relation": "method", "confidence": "EXTRACTED", "source_file": "tests\\unit\\test_context_catch.py", "source_location": "L227", "weight": 1.0}, {"source": "test_context_catch_testsummarizeanswers", "target": "test_context_catch_testsummarizeanswers_test_summarize_answers_multiple", "relation": "method", "confidence": "EXTRACTED", "source_file": "tests\\unit\\test_context_catch.py", "source_location": "L231", "weight": 1.0}, {"source": "tests_unit_test_context_catch_py", "target": "test_context_catch_testsummarizefeedbacks", "relation": "contains", "confidence": "EXTRACTED", "source_file": "tests\\unit\\test_context_catch.py", "source_location": "L237", "weight": 1.0}, {"source": "test_context_catch_testsummarizefeedbacks", "target": "test_context_catch_testsummarizefeedbacks_test_summarize_feedbacks_empty", "relation": "method", "confidence": "EXTRACTED", "source_file": "tests\\unit\\test_context_catch.py", "source_location": "L240", "weight": 1.0}, {"source": "test_context_catch_testsummarizefeedbacks", "target": "test_context_catch_testsummarizefeedbacks_test_summarize_feedbacks_multiple", "relation": "method", "confidence": "EXTRACTED", "source_file": "tests\\unit\\test_context_catch.py", "source_location": "L244", "weight": 1.0}, {"source": "test_context_catch_rationale_1", "target": "tests_unit_test_context_catch_py", "relation": "rationale_for", "confidence": "EXTRACTED", "source_file": "tests\\unit\\test_context_catch.py", "source_location": "L1", "weight": 1.0}, {"source": "test_context_catch_rationale_48", "target": "test_context_catch_testextractprogress", "relation": "rationale_for", "confidence": "EXTRACTED", "source_file": "tests\\unit\\test_context_catch.py", "source_location": "L48", "weight": 1.0}, {"source": "test_context_catch_rationale_68", "target": "test_context_catch_testextractevaluation", "relation": "rationale_for", "confidence": "EXTRACTED", "source_file": "tests\\unit\\test_context_catch.py", "source_location": "L68", "weight": 1.0}, {"source": "test_context_catch_rationale_97", "target": "test_context_catch_testrediskeyfunctions", "relation": "rationale_for", "confidence": "EXTRACTED", "source_file": "tests\\unit\\test_context_catch.py", "source_location": "L97", "weight": 1.0}, {"source": "test_context_catch_rationale_225", "target": "test_context_catch_testsummarizeanswers", "relation": "rationale_for", "confidence": "EXTRACTED", "source_file": "tests\\unit\\test_context_catch.py", "source_location": "L225", "weight": 1.0}, {"source": "test_context_catch_rationale_238", "target": "test_context_catch_testsummarizefeedbacks", "relation": "rationale_for", "confidence": "EXTRACTED", "source_file": "tests\\unit\\test_context_catch.py", "source_location": "L238", "weight": 1.0}]}